{
  "id": "rule-0022",
  "chapterId": "chapter-002",
  "title": "和歌山工業高等専門学校学寮管理運営規則",
  "order": 18,
  "pdfUrl": "https://www.wakayama-nct.ac.jp/media/rules/18gakuryokanrikisoku.pdf",
  "summary": "和歌山工業高等専門学校の学寮管理運営規則で、寮の運営・入寮・退寮・費用・規律・保護者等の手続き等を定めたものです。",
  "sourcePage": null,
  "lastUpdated": null,
  "sections": [
    {
      "id": "rule-0022-section-01",
      "title": "和歌山工業高等専門学校学寮管理運営規則",
      "order": 1,
      "articles": [
        {
          "id": "rule-0022-article-0001",
          "label": "第1条",
          "body": "この規則は、和歌山工業高等専門学校\\(以下「本校」という。\\)における学寮の管理<br>営について必要な事項を定め、その円滑かつ適正な運用を図ることを目的とする。",
          "notes": null,
          "relatedIds": null
        },
        {
          "id": "rule-0022-article-0002",
          "label": "第2条",
          "body": "学寮は、学生の勉学に適する環境において規律ある共同生活を体験させ、これを通じ<br>て人間形成に資する課外教育施設とする。",
          "notes": null,
          "relatedIds": null
        },
        {
          "id": "rule-0022-article-0003",
          "label": "第3条",
          "body": "前項の目的を達成し、かつ、学生の学園生活への適応を促進させるため、学寮に第1<br>学年及び第2学年学生の全員\\(女子学生及び第15条第1項ただし書の規定による学生を除<br>く。\\)を収容する。\n\n2 女子学生及び第3学年以上の男子学生\\(専攻科生を含む。以下同じ。\\)に対しては、選考に<br>より収容する。",
          "notes": null,
          "relatedIds": null
        },
        {
          "id": "rule-0022-article-0004",
          "label": "第4条",
          "body": "学寮に寮務主事を置く。\n\n2 寮務主事は、校長の命を受け、学寮管理運営の責任者として寮生の指導に当たる。\n\n3 寮務主事は、常に学生主事と緊密な連絡を保ち、寮生の指導に遺漏のないように努める。\n\n4 寮務主事は、教授又は准教授をもって充てる。",
          "notes": null,
          "relatedIds": null
        },
        {
          "id": "rule-0022-article-0005",
          "label": "第5条",
          "body": "学寮に寮務主事補を置く。\n\n2 寮務主事補は、寮務主事の下にあって、寮生活の補導及び寮生会その他諸活動の指導に当<br>たる。",
          "notes": null,
          "relatedIds": null
        },
        {
          "id": "rule-0022-article-0006",
          "label": "第6条",
          "body": "学寮に寮父及び寮母を置く。",
          "notes": null,
          "relatedIds": null
        },
        {
          "id": "rule-0022-article-0007",
          "label": "第7条",
          "body": "教員は、校長の命を受けて宿日直を行い、寮生の指導に当たる。",
          "notes": null,
          "relatedIds": null
        },
        {
          "id": "rule-0022-article-0008",
          "label": "第8条",
          "body": "本校の学寮の管理運営に関し具体的な方策を審議し、その円滑な運営を図るため、校<br>長の諮問機関として学寮委員会を置く。\n\n2 学寮委員会は、次に掲げる委員をもって組織し、寮務主事が議長となる。\n\n一 寮務主事\n\n二 寮務主事補\n\n三 その他校長が必要と認める職員\n\n3 学寮委員会に関する事務は、学生課において処理する。",
          "notes": null,
          "relatedIds": null
        },
        {
          "id": "rule-0022-article-0009",
          "label": "第9条",
          "body": "校長は、新入学生全員\\(女子学生及び第15条第1項ただし書の規定による学生を除\n\nく \\)を入学と同時に入客させ、保護者等の連盟を得た入審誓約書\\(様式第1号\\)を提出させ<br>る。\n\n2 保護者等は、寮生の在寮中における行為について、学則及び学寮の諸規則を遵守するよう<br>指導·監督する責任を負うものとする。\n\n3 保護者等は、審生が在寮中に事件·事故等により、その生命若しくは身体に危険を及ぼし、<br>又は財産に重大な損害を及ぼす時、若しくはその恐れのある時には、学校と連携して、寮牛<br>の保護に努めなければならない。\n\n4 保護者等とすることができる者は、寮生が未成年の場合においてはその親権者又は児童福<br>祉法\\(昭和22年法律第164号\\) 第6条、第6条の4及び第7条で定める寮生を監護す<br>る者若しくは監護する施設等の長とする。また、寮生が成年の場合においては3親等以内の<br>親族とする。\n\n5 前項の要件に合った保護者等が選定できない場合は、独立の生計を営む成年者であり、寮牛<br>の指導·支援への意向のある者とする。\n\n6 保護者等が住所等を変更した場合は、入寮誓約書\\(様式第1号\\)により速やかにその旨を<br>校長に届け出なければならない。\n\n7 保護者等が死亡し、又は前第3項の要件に該当しなくなった場合は、新たに保護者等とな<br>る者を定めて、入寮誓約書\\(様式第1号\\)により直ちに校長に提出しなければならない。",
          "notes": null,
          "relatedIds": null
        },
        {
          "id": "rule-0022-article-0010",
          "label": "第10条",
          "body": "女子学生及び第3学以上の男子学生で入寮を希望するものは、指定する日までに、<br>入寮願\\(様式第2号\\)を寮務士事を経て校長に提出しなければならない。\n\n2 入寮を許可すべき者の選考は、寮務主事補の意見を聴いて寮務主事が行う。\n\n3 入寮の許可は、前項の選考の結果に基づいて校長が行う。\n\n4 入寮の許可期間は、1年以内とし、入寮の許可は前項の選考の結果に基づき、校長が年度<br>ごとに行う。",
          "notes": null,
          "relatedIds": null
        },
        {
          "id": "rule-0022-article-0011",
          "label": "第11条",
          "body": "出納命令役は、寮生に寄宿料として、独立行政法人国立高等専門学校機構における<br>授業料その他の費用に関する規則\\(独立行政法人国立高等専門学校機構規則第35号\\)に定<br>める額を納付させる。\n\n2 入退寮の日が月の中途であっても、寄宿料は、1か月分納付させる。\n\n3 休業期間中に係る寄宿料は、第1項の規定にかかわらず、当該期間の開始する月の前月の<br>納入日までに納付させるものとする\n\n4 第1項の規定にかかわらず、学生の申し出又は承諾があったときは、当該年度内に徴収す<br>ろ寄宿料の額の総額の範囲内で その申し出又は承諾に係る額を その際徴収することができ<br>るものとする。\n\n5 寄宿料免除申請のことについては、別に定める規則による。",
          "notes": null,
          "relatedIds": null
        },
        {
          "id": "rule-0022-article-0012",
          "label": "第12条",
          "body": "給食費その他寮生活に必要な光熱水料等の諸経費は、寮生に負担させる。\n\n2 給食費は、給食業務を委託された業者が徴収するものとする。\n\n3 諸経費は、毎月所定の日までに納めなければならない。",
          "notes": null,
          "relatedIds": null
        },
        {
          "id": "rule-0022-article-0013",
          "label": "第13条",
          "body": "寮生に対しては、居室、共用施設その他学寮の施設を常に正常な状態において保全<br>させることに意を用い、次に定めるところに誠実に従わせなければならない。\n\n一 居室を居室以外の目的に使用しないこと。\n\n二 居室に他の者を宿泊させないこと。\n\n三 寮務主事の許可なくして居室に工作を加えないこと。\n\n四 共用の施設は、常に良好な状態を保つよう連帯して保全すること。\n\n五 寮務主事の許可なくして学寮施設に掲示、はり紙等をしないこと。\n\n六 故意又は過失により施設及び設備を滅失し、破損し、又は汚損したときは、その原状回<br>復に必要な経費を弁償させること。\n\n七 防火管理、災害防止対策、保健衛生管理その他学寮施設の管理運営上必要とする学校の<br>指示を守り、積極的にこれに協力すること。",
          "notes": null,
          "relatedIds": null
        },
        {
          "id": "rule-0022-article-0014",
          "label": "第14条",
          "body": "自主的な規律ある寮生活を確立するため、寮生会を組織させる。\n\n2 寮生会会則は、寮務主事の指導の下に作成し、校長の承認を受けるものとする。",
          "notes": null,
          "relatedIds": null
        },
        {
          "id": "rule-0022-article-0015",
          "label": "第15条",
          "body": "第1学年及び第2学年の男子学生に対しては、自己の都合による入寮免除又は退寮は認めない。ただし、病気その他特別な理由により入寮免除願\\(様式第3号\\)を提出した学生に対して、校長が特に認めた場合は、この限りでない。\n\n2 女子寮生及び第3学以上の男子寮生が、退寮を希望するときには、退寮予定日の10日前までに退寮願\\(様式第4号\\)を提出しなければならない。\n\n3 前項の退寮の許可は、寮務主事を経て、校長が行う。\n\n4 退寮の許可を受けた者に対しては、退寮に当たって、居室その他居室に附属する設備等に<br>ついて、校長の指定する職員の検査を受けさせる。",
          "notes": null,
          "relatedIds": null
        },
        {
          "id": "rule-0022-article-0016",
          "label": "第16条",
          "body": "寮生が次の各号のいずれかに該当したときは、校長は、退寮を命ずることができる。\n\n一 3ヶ月以上寄宿料又は第12条に定める経費の納入を怠ったとき。\n\n二 著しく風紀を乱す行為のあったとき。\n\n三 共同生活の秩序を著しく混乱させる行為のあったとき、\n\n四 疾病その他により保健衛生上共同生活に適さないと認めたとき。\n\n五 退学\\(除籍を含む。\\)又は停学を命せられたとき。\n\n六 その他学寮の管理運営上著しく支障をきたす行為のあったとき。",
          "notes": null,
          "relatedIds": null
        },
        {
          "id": "rule-0022-article-0017",
          "label": "第17条",
          "body": "学寮には寮生以外の者を宿泊させない。ただし、やむを得ない理由により特別の願<br>い出があったときは、校長は寮務主事の申出に基づき、使用料の徴収その他法令上の措置に<br>ついて検討の上、日を限り、寮生以外の者を学寮内の適当な部屋に宿泊させることができる。",
          "notes": null,
          "relatedIds": null
        },
        {
          "id": "rule-0022-article-0018",
          "label": "第18条",
          "body": "次の休業日の期間は、原則として学寮を閉寮する。\n\n||–– 春季休業|\n|-|-|\n||二 夏季休業|\n||三 冬季休業|\n\n# 四 学年末休業\n\n2 前項の期間以外における休業日にあっても閉寮することがある。\n\n3 閉寮中においても、寮生が学校行事に参加する場合など、特別な理由により寮務主事が必要と認めた場合には、期間を定め、在寮を認めることがある。",
          "notes": null,
          "relatedIds": null
        },
        {
          "id": "rule-0022-article-0019",
          "label": "第19条",
          "body": "学寮における日常的又は具体的な問題について意見を交換し、職員及び学生の相互の理解を深めるため、寮務主事が必要と認めた場合は、校長の承認を得て懇談会を開催することができる。",
          "notes": null,
          "relatedIds": null
        },
        {
          "id": "rule-0022-article-0020",
          "label": "第20条",
          "body": "この規則の実施に関し必要な規則等は、校長が別に定める。",
          "notes": null,
          "relatedIds": null
        },
        {
          "id": "rule-0022-article-0021",
          "label": null,
          "body": "1 この規則は、昭和43年4月1日から施行する。",
          "notes": null,
          "relatedIds": null
        },
        {
          "id": "rule-0022-article-0022",
          "label": null,
          "body": "2 この規則中、第1学年及び第2学年生全寮制に関する条文において、昭和42年度以前に入学し、昭和43年度以降に第2学年若しくは第1学年に在学する学生の取扱いについては、昭和43年度新入生のそれに準じて適用し、運用するものとする。",
          "notes": null,
          "relatedIds": null
        },
        {
          "id": "rule-0022-article-0023",
          "label": null,
          "body": "附 則\n\nこの規則は、昭和45年4月1日から施行する。",
          "notes": null,
          "relatedIds": null
        },
        {
          "id": "rule-0022-article-0024",
          "label": null,
          "body": "附 則\n\nこの規則は、昭和48年10月11日から施行し、第6条及び第9条は、昭和48年4月1日から適用する。",
          "notes": null,
          "relatedIds": null
        },
        {
          "id": "rule-0022-article-0025",
          "label": null,
          "body": "附 則\n\nこの規則は、昭和50年4月1日から施行する。",
          "notes": null,
          "relatedIds": null
        },
        {
          "id": "rule-0022-article-0026",
          "label": null,
          "body": "附 則\n\nこの規則は、昭和58年12月15日から施行する",
          "notes": null,
          "relatedIds": null
        },
        {
          "id": "rule-0022-article-0027",
          "label": null,
          "body": "附 則\n\nこの規則は、昭和63年4月7日から施行し、昭和63年4月1日から適用する。",
          "notes": null,
          "relatedIds": null
        },
        {
          "id": "rule-0022-article-0028",
          "label": null,
          "body": "附 則\n\nこの規則は、平成10年4月1日から施行する。",
          "notes": null,
          "relatedIds": null
        },
        {
          "id": "rule-0022-article-0029",
          "label": null,
          "body": "附 則\n\nこの規則は、平成11年1月27日から施行する。",
          "notes": null,
          "relatedIds": null
        },
        {
          "id": "rule-0022-article-0030",
          "label": null,
          "body": "附 則\n\nこの規則は、平成11年4月1日から施行する。",
          "notes": null,
          "relatedIds": null
        },
        {
          "id": "rule-0022-article-0031",
          "label": null,
          "body": "附 則\n\nこの規則は、平成13年2月14日から施行し、平成13年1月6日から適用する,",
          "notes": null,
          "relatedIds": null
        },
        {
          "id": "rule-0022-article-0032",
          "label": null,
          "body": "附 則\n\nこの規則は、平成15年4月1日から施行する。",
          "notes": null,
          "relatedIds": null
        },
        {
          "id": "rule-0022-article-0033",
          "label": null,
          "body": "附 則\n\nこの規則は、平成16年4月1日から施行する。",
          "notes": null,
          "relatedIds": null
        },
        {
          "id": "rule-0022-article-0034",
          "label": null,
          "body": "附 則\n\nこの規則は、平成18年4月1日から施行する。",
          "notes": null,
          "relatedIds": null
        },
        {
          "id": "rule-0022-article-0035",
          "label": null,
          "body": "附 則\n\nこの規則は、平成27年4月1日から施行する。",
          "notes": null,
          "relatedIds": null
        },
        {
          "id": "rule-0022-article-0036",
          "label": null,
          "body": "附 則\n\nこの規則は、令和 3年3月8日から施行する。",
          "notes": null,
          "relatedIds": null
        }
      ]
    }
  ],
  "articles": [
    {
      "id": "rule-0022-article-0037",
      "label": null,
      "body": "様式第1号\n\n# 入 寮 誓 約 書\n\n和歌山工業高等専門学校長 様\n\n# 様式第2号\n\n曽校学生寮に入寮の上は学則及び学生寮の諸規則が在春中は適用される~<br>和歌山工業高等専門学校長 様<br>とについて同意し、諸規則を遵守することを誓います。\n\n\\(元号\\)<br>) 年 月 日\n\n和歌山工業高等専門学校<br>学科<br>氏 名 \\(自署\\)\n\n私は、「独立行政法人国立高等専門学校機構保護者等に関する取扱要項<br>\\(令和3年2月18日理事長裁定\\)に基づき、上記の者が貴校の学生寮に在<br>寮中における行為について、学則及び学生寮の諸規則を遵守するよう指導·<br>監督する責任を負うことを誓約します\\.\n\nなお、記載事項に変更が生じたときは、すみやかに本書を再提出いたします。\n\n\\(保護者等\\)<br>住 所<br>学生との関係<br>氏 名 \\(自署\\)<br>緊急連絡先\n\n保護者等とは、学生が教育研究活動を円滑に遂行していくうえて、学校と連携し、学生を指導,支援する立場にある者で、学生が未成年の場合においてはその親権者又は児童福祉法\\(昭和22年法律第<br>164号\\)第6条,第6条の4及び第7条で定める学生を監護する<br>者若しくは監護する施設等の長とする。また、学生が成年の場合においては3親等以内の親族とする。要件に合った保護者等が選定できない場合は、独立の生計を営む成年者であり,学生の指導,支援への意向のある者とする。\n\n入 寮 願\n\n\\(元号\\)<br>) 年 月 日\n\n学科 第 学年<br>氏 名\\(自署\\)<br>\\(元号\\)<br>) 年 月 日生<br>住 所\\(自宅\\)\n\n保護者等<br>氏 名 \\(自署\\)<br>本人との続柄<br>住 所\n\n下記の事由により、入寮したいので、御許可下さるようお願いします。<br>なお、入寮のうえは、学寮における諸規則を固く守ることを誓います。\n\n1 事 由\n\n記\n\n2 入寮希望年月日<br>\\(元号\\)<br>年 月 日<br>※ 入寮年月日<br>\\(元号\\)<br>年 月 日\n\n様式第3号\n\n入 寮 免 除 願\n\n和歌山工業高等専門学校長 様\n\n\\(元号\\)<br>年 月 日\n\n学科 第 学年\n\n氏 名 \\(自署\\)\n\n\\(元号\\)<br>年 月 日生\n\n住 所\\(自宅\\)\n\n保護者等\n\n氏 名 \\(自署\\)\n\n# 様式第4号\n\n退 寮 順\n\n# 和歌山工業高等専門学校長 様\n\n担任印\n\n\\(元号\\)<br>年 月 日\n\n学科 第<br>亨 学年<br>氏 名 \\(自署\\)<br>\\(元号\\)<br>年 月 日生<br>学寮室番号<br>号館 号室<br>入寮年月日\\(元号\\) 年 月 日<br>保護者等氏名\\(自署\\)<br>住 所\n\n住 所<br>保護者等氏名\\(自署\\)\n\nこのたび、下記の事由により、入寮を免除して下さるようお願いします。\n\n1 事 由\n\n記\n\n2 期 間<br>\\(元号\\)<br>日から\n\n下記事由により、退寮したいので、御許可下さるようお願いします。\n\n記\n\n1 事 由\n\n\\(元号\\)<br>年 月<br>日まで\n\n2\n\n退寮希望年月日\n\n\\(元号\\)<br>年 月 日\\( \\)\n\n\\(注\\) 1\n\n免除の事由を証する証明書等の提出を求めることがある。<br>3",
      "notes": null,
      "relatedIds": null
    }
  ],
  "relatedIds": null
}